dataclass_binder/__init__.py
dataclass_binder/_impl.py
dataclass_binder/py.typed
dataclass_binder-0.3.4.dist-info/LICENSE
dataclass_binder-0.3.4.dist-info/METADATA
dataclass_binder-0.3.4.dist-info/WHEEL
dataclass_binder-0.3.4.dist-info/RECORD
