Metadata-Version: 2.1
Name: dataclass-binder
Version: 0.3.4
Summary: Library to bind TOML data to Python dataclasses in a type-safe way.
Home-page: https://github.com/ProtixIT/dataclass-binder
License: MIT
Keywords: dataclass,toml,bind,binding
Author: Maarten ter Huurne
Author-email: maarten.terhuurne@protix.eu
Requires-Python: >=3.10,<4.0
Classifier: Intended Audience :: Developers
Classifier: License :: OSI Approved :: MIT License
Classifier: Programming Language :: Python :: 3
Classifier: Programming Language :: Python :: 3.10
Classifier: Programming Language :: Python :: 3.11
Classifier: Topic :: Software Development :: Libraries :: Python Modules
Requires-Dist: tomli (>=2.0.1,<3.0.0) ; python_version < "3.11"
Project-URL: Issue Tracker, https://github.com/ProtixIT/dataclass-binder/issues
Project-URL: Repository, https://github.com/ProtixIT/dataclass-binder
